{
  "$id": "https://schemas.dissco.tech/schemas/elvis/ltc_profile/entities/facility",
  "type": "object",
  "properties": {
    "ltc:hasOrganisationalUnit": {
      "$ref": "../definitions/organisationalUnit.schema.json"
    },
    "schema:image": {
      "type": "array",
      "items": {
        "type": "string",
        "format": "uri"
      }
    },
    "ltc:identifier": {
      "$ref": "../definitions/identifier.schema.json"
    },
    "ltc:address": {
      "$ref": "../definitions/address.schema.json"
    }
  },
  "required": [
    "ltc:hasOrganisationalUnit"
  ]
}